{
  "company_name": "Yara International ASA",
  "ticker": "YAR.OL",
  "current_price": 377.1,
  "market_cap": "96.1 mrd NOK",
  "market_cap_raw": 96057040896,
  "sector": "Basic Materials",
  "industry": "Agricultural Inputs",
  "employees": 16624,
  "headquarters": "Oslo, Norway",
  "description": "Yara International ASA provides crop nutrition and industrial solutions in Norway, European Union, Europe, Africa, Asia, North and Latin America, Australia, and New Zealand. The company offers ammonium- and urea-based fertilizers; compound fertilizers that contain nutrients, such as nitrogen, phosphorus, and potassium; coatings; biostimulants; organic-based fertilizers; green fertilizers are nitrate-based mineral fertilizers, as well as foliar and fertigation solutions; and nitrate, calcium nitrate, micronutrient, and fertigation and urea fertilizers. It also offers digital solutions, such as variable rate application solutions; N-sensors, a tractor-mounted hardware; N-Tester, a handheld nitrogen measurement tool; YaraFX Insight, an agricultural API; and Atfarm, a digital toolbox for farmer; Yara FarmCare, a mobile app for farmers; Yara AllFarm, a farm management platform; YaraConnect, a mobile app for retailers; Yara E-commerce, a platform that enables customer access to nutritional solutions; Tankmix, an app that provides guidelines. Further, it offers Yara Crop Nutrition Recommendation System. The company sells its products under YaraBela, YaraMila, YaraLiva, YaraVita, YaraAmplix, YaraRega, YaraTera, YaraSuna, and YaraVera and brands. Yara International ASA was founded in 1905 and is headquartered in Oslo, Norway.",
  "price_52w_high": 403.0,
  "price_52w_low": 282.2,
  "performance_5y": 6.66,
  "performance_2y": -6.91,
  "performance_1y": 16.3,
  "volatility": 33.94,
  "revenue_2024": 14595000320,
  "revenue_2024_formatted": "15 mrd NOK",
  "ebitda_2024": 1884000000,
  "ebitda_2024_formatted": "2 mrd NOK",
  "net_earnings_2024": 701000000,
  "net_earnings_2024_formatted": "701 mill NOK",
  "pe_ratio": 13.772827,
  "pe_ratio_formatted": "13.77",
  "ps_ratio": 6.5815034,
  "ps_ratio_formatted": "6.58",
  "ev_ebitda": 52.765,
  "ev_ebitda_formatted": "52.77",
  "chart_data": [
    {
      "date": "2020-09-25",
      "price": 351.1,
      "high": 356.6,
      "low": 350.1,
      "volume": 441921
    },
    {
      "date": "2020-09-29",
      "price": 358.7,
      "high": 358.7,
      "low": 352.6,
      "volume": 465243
    },
    {
      "date": "2020-10-01",
      "price": 355.4,
      "high": 359.2,
      "low": 355.0,
      "volume": 448745
    },
    {
      "date": "2020-10-05",
      "price": 360.8,
      "high": 362.5,
      "low": 358.3,
      "volume": 515943
    },
    {
      "date": "2020-10-07",
      "price": 352.3,
      "high": 356.1,
      "low": 349.1,
      "volume": 676039
    },
    {
      "date": "2020-10-09",
      "price": 348.0,
      "high": 355.4,
      "low": 347.4,
      "volume": 791580
    },
    {
      "date": "2020-10-13",
      "price": 345.2,
      "high": 350.0,
      "low": 344.7,
      "volume": 523001
    },
    {
      "date": "2020-10-15",
      "price": 341.8,
      "high": 345.1,
      "low": 341.4,
      "volume": 562938
    },
    {
      "date": "2020-10-19",
      "price": 344.8,
      "high": 350.2,
      "low": 344.7,
      "volume": 599528
    },
    {
      "date": "2020-10-21",
      "price": 340.8,
      "high": 343.6,
      "low": 338.2,
      "volume": 878770
    },
    {
      "date": "2020-10-23",
      "price": 345.6,
      "high": 346.7,
      "low": 340.5,
      "volume": 766793
    },
    {
      "date": "2020-10-27",
      "price": 332.9,
      "high": 339.3,
      "low": 332.9,
      "volume": 768712
    },
    {
      "date": "2020-10-29",
      "price": 335.4,
      "high": 335.4,
      "low": 327.9,
      "volume": 615570
    },
    {
      "date": "2020-11-02",
      "price": 339.3,
      "high": 339.7,
      "low": 331.5,
      "volume": 492384
    },
    {
      "date": "2020-11-04",
      "price": 341.6,
      "high": 343.2,
      "low": 334.0,
      "volume": 607973
    },
    {
      "date": "2020-11-06",
      "price": 346.5,
      "high": 347.8,
      "low": 344.1,
      "volume": 439677
    },
    {
      "date": "2020-11-10",
      "price": 356.4,
      "high": 356.4,
      "low": 351.0,
      "volume": 802449
    },
    {
      "date": "2020-11-12",
      "price": 364.2,
      "high": 365.4,
      "low": 361.3,
      "volume": 482730
    },
    {
      "date": "2020-11-16",
      "price": 382.5,
      "high": 382.5,
      "low": 370.1,
      "volume": 1011899
    },
    {
      "date": "2020-11-18",
      "price": 367.8,
      "high": 369.5,
      "low": 361.9,
      "volume": 910752
    },
    {
      "date": "2020-11-20",
      "price": 363.8,
      "high": 367.4,
      "low": 360.5,
      "volume": 610305
    },
    {
      "date": "2020-11-24",
      "price": 373.4,
      "high": 373.4,
      "low": 368.0,
      "volume": 506597
    },
    {
      "date": "2020-11-26",
      "price": 362.2,
      "high": 364.3,
      "low": 359.6,
      "volume": 606236
    },
    {
      "date": "2020-11-30",
      "price": 359.8,
      "high": 365.5,
      "low": 359.6,
      "volume": 961430
    },
    {
      "date": "2020-12-02",
      "price": 357.9,
      "high": 362.0,
      "low": 354.3,
      "volume": 590560
    },
    {
      "date": "2020-12-04",
      "price": 355.6,
      "high": 359.2,
      "low": 354.1,
      "volume": 588233
    },
    {
      "date": "2020-12-08",
      "price": 357.5,
      "high": 365.3,
      "low": 357.1,
      "volume": 545888
    },
    {
      "date": "2020-12-10",
      "price": 357.5,
      "high": 359.9,
      "low": 356.9,
      "volume": 499420
    },
    {
      "date": "2020-12-14",
      "price": 348.4,
      "high": 357.9,
      "low": 347.2,
      "volume": 751508
    },
    {
      "date": "2020-12-16",
      "price": 354.0,
      "high": 354.0,
      "low": 351.1,
      "volume": 518565
    },
    {
      "date": "2020-12-18",
      "price": 354.0,
      "high": 358.3,
      "low": 353.3,
      "volume": 787618
    },
    {
      "date": "2020-12-22",
      "price": 352.2,
      "high": 352.7,
      "low": 349.0,
      "volume": 424351
    },
    {
      "date": "2020-12-28",
      "price": 359.0,
      "high": 359.3,
      "low": 355.5,
      "volume": 335470
    },
    {
      "date": "2020-12-30",
      "price": 356.0,
      "high": 358.1,
      "low": 355.4,
      "volume": 349188
    },
    {
      "date": "2021-01-05",
      "price": 360.7,
      "high": 364.4,
      "low": 359.4,
      "volume": 678727
    },
    {
      "date": "2021-01-07",
      "price": 386.6,
      "high": 387.6,
      "low": 372.7,
      "volume": 1124958
    },
    {
      "date": "2021-01-11",
      "price": 380.8,
      "high": 385.8,
      "low": 377.8,
      "volume": 700831
    },
    {
      "date": "2021-01-13",
      "price": 382.9,
      "high": 383.6,
      "low": 375.9,
      "volume": 839894
    },
    {
      "date": "2021-01-15",
      "price": 386.9,
      "high": 389.4,
      "low": 384.0,
      "volume": 862464
    },
    {
      "date": "2021-01-19",
      "price": 394.0,
      "high": 397.5,
      "low": 387.9,
      "volume": 723964
    },
    {
      "date": "2021-01-21",
      "price": 390.7,
      "high": 394.5,
      "low": 389.5,
      "volume": 389607
    },
    {
      "date": "2021-01-25",
      "price": 383.0,
      "high": 392.2,
      "low": 380.4,
      "volume": 669360
    },
    {
      "date": "2021-01-27",
      "price": 388.0,
      "high": 392.4,
      "low": 380.0,
      "volume": 1100388
    },
    {
      "date": "2021-01-29",
      "price": 400.5,
      "high": 402.7,
      "low": 388.6,
      "volume": 1359385
    },
    {
      "date": "2021-02-02",
      "price": 399.8,
      "high": 404.6,
      "low": 398.0,
      "volume": 707067
    },
    {
      "date": "2021-02-04",
      "price": 405.1,
      "high": 406.0,
      "low": 402.0,
      "volume": 397845
    },
    {
      "date": "2021-02-08",
      "price": 417.3,
      "high": 417.7,
      "low": 408.0,
      "volume": 665692
    },
    {
      "date": "2021-02-10",
      "price": 417.1,
      "high": 421.0,
      "low": 413.2,
      "volume": 875375
    },
    {
      "date": "2021-02-12",
      "price": 413.7,
      "high": 423.0,
      "low": 412.5,
      "volume": 556239
    },
    {
      "date": "2021-02-16",
      "price": 419.9,
      "high": 420.8,
      "low": 413.8,
      "volume": 477996
    },
    {
      "date": "2021-02-18",
      "price": 411.6,
      "high": 420.2,
      "low": 410.7,
      "volume": 552946
    },
    {
      "date": "2021-02-22",
      "price": 424.7,
      "high": 426.8,
      "low": 415.0,
      "volume": 451691
    },
    {
      "date": "2021-02-24",
      "price": 427.0,
      "high": 427.7,
      "low": 420.7,
      "volume": 446140
    },
    {
      "date": "2021-02-26",
      "price": 416.6,
      "high": 420.8,
      "low": 414.8,
      "volume": 642782
    },
    {
      "date": "2021-03-02",
      "price": 425.5,
      "high": 427.7,
      "low": 421.5,
      "volume": 353015
    },
    {
      "date": "2021-03-04",
      "price": 419.5,
      "high": 429.8,
      "low": 419.2,
      "volume": 427247
    },
    {
      "date": "2021-03-08",
      "price": 432.1,
      "high": 432.5,
      "low": 420.9,
      "volume": 697567
    },
    {
      "date": "2021-03-10",
      "price": 432.5,
      "high": 436.0,
      "low": 428.9,
      "volume": 479820
    },
    {
      "date": "2021-03-12",
      "price": 438.1,
      "high": 439.0,
      "low": 432.9,
      "volume": 484125
    },
    {
      "date": "2021-03-16",
      "price": 433.2,
      "high": 436.8,
      "low": 431.8,
      "volume": 462266
    },
    {
      "date": "2021-03-18",
      "price": 436.9,
      "high": 437.6,
      "low": 429.4,
      "volume": 442820
    },
    {
      "date": "2021-03-22",
      "price": 441.0,
      "high": 444.0,
      "low": 435.2,
      "volume": 586697
    },
    {
      "date": "2021-03-24",
      "price": 431.9,
      "high": 436.0,
      "low": 427.8,
      "volume": 449879
    },
    {
      "date": "2021-03-26",
      "price": 444.0,
      "high": 447.2,
      "low": 439.4,
      "volume": 539456
    },
    {
      "date": "2021-03-30",
      "price": 447.2,
      "high": 451.3,
      "low": 444.2,
      "volume": 515599
    },
    {
      "date": "2021-04-06",
      "price": 438.7,
      "high": 448.4,
      "low": 436.9,
      "volume": 867991
    },
    {
      "date": "2021-04-08",
      "price": 432.3,
      "high": 436.3,
      "low": 428.2,
      "volume": 488474
    },
    {
      "date": "2021-04-12",
      "price": 426.5,
      "high": 429.4,
      "low": 423.7,
      "volume": 568115
    },
    {
      "date": "2021-04-14",
      "price": 430.1,
      "high": 430.1,
      "low": 424.8,
      "volume": 481945
    },
    {
      "date": "2021-04-16",
      "price": 442.1,
      "high": 445.1,
      "low": 438.8,
      "volume": 616768
    },
    {
      "date": "2021-04-20",
      "price": 436.1,
      "high": 440.6,
      "low": 432.3,
      "volume": 534354
    },
    {
      "date": "2021-04-22",
      "price": 441.2,
      "high": 446.2,
      "low": 440.0,
      "volume": 562103
    },
    {
      "date": "2021-04-26",
      "price": 429.4,
      "high": 430.0,
      "low": 419.3,
      "volume": 802051
    },
    {
      "date": "2021-04-28",
      "price": 441.7,
      "high": 442.3,
      "low": 433.5,
      "volume": 482623
    },
    {
      "date": "2021-04-30",
      "price": 434.7,
      "high": 439.9,
      "low": 434.2,
      "volume": 525649
    },
    {
      "date": "2021-05-04",
      "price": 435.4,
      "high": 440.1,
      "low": 433.6,
      "volume": 390550
    },
    {
      "date": "2021-05-06",
      "price": 423.2,
      "high": 448.5,
      "low": 440.7,
      "volume": 780965
    },
    {
      "date": "2021-05-10",
      "price": 438.0,
      "high": 438.8,
      "low": 425.6,
      "volume": 586968
    },
    {
      "date": "2021-05-12",
      "price": 442.5,
      "high": 442.5,
      "low": 433.5,
      "volume": 611811
    },
    {
      "date": "2021-05-18",
      "price": 451.5,
      "high": 452.6,
      "low": 445.2,
      "volume": 664975
    },
    {
      "date": "2021-05-20",
      "price": 437.6,
      "high": 442.4,
      "low": 437.6,
      "volume": 508082
    },
    {
      "date": "2021-05-25",
      "price": 436.5,
      "high": 444.9,
      "low": 435.6,
      "volume": 604172
    },
    {
      "date": "2021-05-27",
      "price": 439.5,
      "high": 442.2,
      "low": 432.9,
      "volume": 918200
    },
    {
      "date": "2021-05-31",
      "price": 445.3,
      "high": 449.2,
      "low": 443.8,
      "volume": 408767
    },
    {
      "date": "2021-06-02",
      "price": 449.4,
      "high": 454.3,
      "low": 449.2,
      "volume": 442439
    },
    {
      "date": "2021-06-04",
      "price": 455.9,
      "high": 455.9,
      "low": 450.0,
      "volume": 439321
    },
    {
      "date": "2021-06-08",
      "price": 467.8,
      "high": 471.2,
      "low": 465.7,
      "volume": 356948
    },
    {
      "date": "2021-06-10",
      "price": 465.5,
      "high": 468.4,
      "low": 463.6,
      "volume": 364383
    },
    {
      "date": "2021-06-14",
      "price": 471.1,
      "high": 473.8,
      "low": 469.5,
      "volume": 317002
    },
    {
      "date": "2021-06-16",
      "price": 471.7,
      "high": 475.2,
      "low": 465.3,
      "volume": 433807
    },
    {
      "date": "2021-06-18",
      "price": 459.2,
      "high": 468.2,
      "low": 458.3,
      "volume": 855132
    },
    {
      "date": "2021-06-22",
      "price": 470.4,
      "high": 473.2,
      "low": 466.3,
      "volume": 645000
    },
    {
      "date": "2021-06-24",
      "price": 469.6,
      "high": 473.9,
      "low": 469.2,
      "volume": 391280
    },
    {
      "date": "2021-06-28",
      "price": 459.7,
      "high": 471.8,
      "low": 456.4,
      "volume": 435173
    },
    {
      "date": "2021-06-30",
      "price": 453.2,
      "high": 460.3,
      "low": 453.2,
      "volume": 762202
    },
    {
      "date": "2021-07-02",
      "price": 461.9,
      "high": 462.9,
      "low": 459.8,
      "volume": 415446
    },
    {
      "date": "2021-07-06",
      "price": 464.0,
      "high": 468.6,
      "low": 464.0,
      "volume": 338282
    },
    {
      "date": "2021-07-08",
      "price": 468.1,
      "high": 472.3,
      "low": 464.3,
      "volume": 672321
    },
    {
      "date": "2021-07-12",
      "price": 476.3,
      "high": 479.1,
      "low": 472.2,
      "volume": 305360
    },
    {
      "date": "2021-07-14",
      "price": 492.0,
      "high": 492.0,
      "low": 480.8,
      "volume": 674856
    },
    {
      "date": "2021-07-16",
      "price": 470.8,
      "high": 498.4,
      "low": 470.8,
      "volume": 680613
    },
    {
      "date": "2021-07-20",
      "price": 477.2,
      "high": 477.2,
      "low": 466.7,
      "volume": 521053
    },
    {
      "date": "2021-07-22",
      "price": 467.5,
      "high": 472.4,
      "low": 464.2,
      "volume": 410259
    },
    {
      "date": "2021-07-26",
      "price": 472.8,
      "high": 474.8,
      "low": 469.0,
      "volume": 306080
    },
    {
      "date": "2021-07-28",
      "price": 467.8,
      "high": 473.0,
      "low": 465.5,
      "volume": 323737
    },
    {
      "date": "2021-07-30",
      "price": 465.3,
      "high": 466.7,
      "low": 458.3,
      "volume": 445825
    },
    {
      "date": "2021-08-03",
      "price": 459.0,
      "high": 462.3,
      "low": 454.6,
      "volume": 478208
    },
    {
      "date": "2021-08-05",
      "price": 456.4,
      "high": 464.4,
      "low": 454.4,
      "volume": 341262
    },
    {
      "date": "2021-08-09",
      "price": 448.0,
      "high": 455.0,
      "low": 446.0,
      "volume": 409981
    },
    {
      "date": "2021-08-11",
      "price": 448.9,
      "high": 454.9,
      "low": 448.9,
      "volume": 350897
    },
    {
      "date": "2021-08-13",
      "price": 451.2,
      "high": 452.3,
      "low": 447.5,
      "volume": 335203
    },
    {
      "date": "2021-08-17",
      "price": 448.1,
      "high": 456.1,
      "low": 446.1,
      "volume": 424318
    },
    {
      "date": "2021-08-19",
      "price": 447.6,
      "high": 447.7,
      "low": 442.3,
      "volume": 519843
    },
    {
      "date": "2021-08-23",
      "price": 455.9,
      "high": 455.9,
      "low": 449.0,
      "volume": 346563
    },
    {
      "date": "2021-08-25",
      "price": 454.2,
      "high": 454.4,
      "low": 448.1,
      "volume": 339126
    },
    {
      "date": "2021-08-27",
      "price": 447.6,
      "high": 448.5,
      "low": 443.1,
      "volume": 336438
    },
    {
      "date": "2021-08-31",
      "price": 436.6,
      "high": 447.5,
      "low": 436.2,
      "volume": 903789
    },
    {
      "date": "2021-09-02",
      "price": 438.3,
      "high": 441.9,
      "low": 434.3,
      "volume": 512844
    },
    {
      "date": "2021-09-06",
      "price": 422.0,
      "high": 442.4,
      "low": 437.0,
      "volume": 574863
    },
    {
      "date": "2021-09-08",
      "price": 409.5,
      "high": 413.4,
      "low": 407.3,
      "volume": 761006
    },
    {
      "date": "2021-09-10",
      "price": 405.6,
      "high": 410.8,
      "low": 403.5,
      "volume": 420791
    },
    {
      "date": "2021-09-14",
      "price": 411.1,
      "high": 415.4,
      "low": 405.7,
      "volume": 522262
    },
    {
      "date": "2021-09-16",
      "price": 420.5,
      "high": 424.9,
      "low": 414.6,
      "volume": 709483
    },
    {
      "date": "2021-09-20",
      "price": 400.9,
      "high": 402.0,
      "low": 394.7,
      "volume": 870737
    },
    {
      "date": "2021-09-22",
      "price": 408.6,
      "high": 410.5,
      "low": 404.7,
      "volume": 518321
    },
    {
      "date": "2021-09-24",
      "price": 429.4,
      "high": 429.9,
      "low": 419.8,
      "volume": 772537
    },
    {
      "date": "2021-09-28",
      "price": 425.0,
      "high": 434.2,
      "low": 424.9,
      "volume": 574923
    },
    {
      "date": "2021-09-30",
      "price": 434.3,
      "high": 441.0,
      "low": 432.6,
      "volume": 1003303
    },
    {
      "date": "2021-10-04",
      "price": 433.8,
      "high": 440.0,
      "low": 429.0,
      "volume": 612411
    },
    {
      "date": "2021-10-06",
      "price": 411.8,
      "high": 425.0,
      "low": 405.7,
      "volume": 902894
    },
    {
      "date": "2021-10-08",
      "price": 420.7,
      "high": 423.3,
      "low": 417.0,
      "volume": 351959
    },
    {
      "date": "2021-10-12",
      "price": 427.9,
      "high": 429.7,
      "low": 424.2,
      "volume": 431354
    },
    {
      "date": "2021-10-14",
      "price": 429.8,
      "high": 429.8,
      "low": 425.3,
      "volume": 402529
    },
    {
      "date": "2021-10-18",
      "price": 430.0,
      "high": 434.3,
      "low": 425.6,
      "volume": 658845
    },
    {
      "date": "2021-10-20",
      "price": 434.5,
      "high": 436.7,
      "low": 420.2,
      "volume": 852937
    },
    {
      "date": "2021-10-22",
      "price": 430.7,
      "high": 432.8,
      "low": 424.5,
      "volume": 525276
    },
    {
      "date": "2021-10-26",
      "price": 420.0,
      "high": 430.8,
      "low": 418.2,
      "volume": 559773
    },
    {
      "date": "2021-10-28",
      "price": 436.9,
      "high": 437.0,
      "low": 424.4,
      "volume": 682096
    },
    {
      "date": "2021-11-01",
      "price": 440.5,
      "high": 448.0,
      "low": 439.4,
      "volume": 591081
    },
    {
      "date": "2021-11-03",
      "price": 455.8,
      "high": 461.5,
      "low": 445.0,
      "volume": 906489
    },
    {
      "date": "2021-11-05",
      "price": 461.0,
      "high": 465.5,
      "low": 458.7,
      "volume": 427065
    },
    {
      "date": "2021-11-09",
      "price": 461.4,
      "high": 468.2,
      "low": 459.3,
      "volume": 448283
    },
    {
      "date": "2021-11-11",
      "price": 463.3,
      "high": 473.8,
      "low": 460.6,
      "volume": 864801
    },
    {
      "date": "2021-11-15",
      "price": 451.0,
      "high": 463.3,
      "low": 450.2,
      "volume": 569965
    },
    {
      "date": "2021-11-17",
      "price": 446.5,
      "high": 451.6,
      "low": 445.4,
      "volume": 432575
    },
    {
      "date": "2021-11-19",
      "price": 446.3,
      "high": 449.2,
      "low": 442.0,
      "volume": 612404
    },
    {
      "date": "2021-11-23",
      "price": 451.6,
      "high": 454.0,
      "low": 444.0,
      "volume": 433624
    },
    {
      "date": "2021-11-25",
      "price": 447.2,
      "high": 449.3,
      "low": 444.9,
      "volume": 413235
    },
    {
      "date": "2021-11-29",
      "price": 445.4,
      "high": 448.3,
      "low": 439.2,
      "volume": 483377
    },
    {
      "date": "2021-12-01",
      "price": 447.2,
      "high": 451.9,
      "low": 443.5,
      "volume": 417560
    },
    {
      "date": "2021-12-03",
      "price": 441.9,
      "high": 441.9,
      "low": 435.8,
      "volume": 690642
    },
    {
      "date": "2021-12-07",
      "price": 456.4,
      "high": 457.0,
      "low": 447.5,
      "volume": 609396
    },
    {
      "date": "2021-12-09",
      "price": 450.8,
      "high": 454.6,
      "low": 448.2,
      "volume": 341937
    },
    {
      "date": "2021-12-13",
      "price": 447.8,
      "high": 461.1,
      "low": 447.4,
      "volume": 470775
    },
    {
      "date": "2021-12-15",
      "price": 448.4,
      "high": 452.4,
      "low": 443.0,
      "volume": 427869
    },
    {
      "date": "2021-12-17",
      "price": 448.7,
      "high": 456.2,
      "low": 448.4,
      "volume": 1019061
    },
    {
      "date": "2021-12-21",
      "price": 442.4,
      "high": 455.1,
      "low": 441.8,
      "volume": 494136
    },
    {
      "date": "2021-12-23",
      "price": 445.0,
      "high": 446.0,
      "low": 432.0,
      "volume": 498091
    },
    {
      "date": "2021-12-28",
      "price": 450.0,
      "high": 451.4,
      "low": 448.3,
      "volume": 232455
    },
    {
      "date": "2021-12-30",
      "price": 445.0,
      "high": 449.8,
      "low": 444.0,
      "volume": 416164
    },
    {
      "date": "2022-01-04",
      "price": 463.0,
      "high": 471.7,
      "low": 460.0,
      "volume": 428986
    },
    {
      "date": "2022-01-06",
      "price": 451.6,
      "high": 469.3,
      "low": 451.6,
      "volume": 951724
    },
    {
      "date": "2022-01-10",
      "price": 451.0,
      "high": 457.3,
      "low": 446.4,
      "volume": 565022
    },
    {
      "date": "2022-01-12",
      "price": 473.0,
      "high": 477.0,
      "low": 462.4,
      "volume": 771167
    },
    {
      "date": "2022-01-14",
      "price": 477.0,
      "high": 481.6,
      "low": 473.6,
      "volume": 738922
    },
    {
      "date": "2022-01-18",
      "price": 487.1,
      "high": 488.7,
      "low": 475.2,
      "volume": 462782
    },
    {
      "date": "2022-01-20",
      "price": 465.0,
      "high": 475.0,
      "low": 461.2,
      "volume": 554049
    },
    {
      "date": "2022-01-24",
      "price": 439.1,
      "high": 458.5,
      "low": 438.0,
      "volume": 422228
    },
    {
      "date": "2022-01-26",
      "price": 461.5,
      "high": 465.5,
      "low": 451.1,
      "volume": 583327
    },
    {
      "date": "2022-01-28",
      "price": 463.9,
      "high": 470.1,
      "low": 456.7,
      "volume": 589270
    },
    {
      "date": "2022-02-01",
      "price": 461.9,
      "high": 465.6,
      "low": 454.5,
      "volume": 484839
    },
    {
      "date": "2022-02-03",
      "price": 466.2,
      "high": 479.8,
      "low": 463.0,
      "volume": 513146
    },
    {
      "date": "2022-02-07",
      "price": 466.4,
      "high": 474.1,
      "low": 465.4,
      "volume": 728606
    },
    {
      "date": "2022-02-09",
      "price": 442.6,
      "high": 442.7,
      "low": 430.1,
      "volume": 1412020
    },
    {
      "date": "2022-02-11",
      "price": 449.6,
      "high": 449.6,
      "low": 427.6,
      "volume": 1313398
    },
    {
      "date": "2022-02-15",
      "price": 441.7,
      "high": 448.8,
      "low": 439.5,
      "volume": 790607
    },
    {
      "date": "2022-02-17",
      "price": 444.9,
      "high": 451.6,
      "low": 442.3,
      "volume": 612063
    },
    {
      "date": "2022-02-21",
      "price": 431.6,
      "high": 448.1,
      "low": 430.4,
      "volume": 977495
    },
    {
      "date": "2022-02-23",
      "price": 423.2,
      "high": 434.0,
      "low": 423.2,
      "volume": 700826
    },
    {
      "date": "2022-02-25",
      "price": 429.5,
      "high": 439.0,
      "low": 428.0,
      "volume": 768542
    },
    {
      "date": "2022-03-01",
      "price": 453.0,
      "high": 456.5,
      "low": 444.1,
      "volume": 853272
    },
    {
      "date": "2022-03-03",
      "price": 448.1,
      "high": 461.1,
      "low": 444.2,
      "volume": 811589
    },
    {
      "date": "2022-03-07",
      "price": 414.4,
      "high": 423.8,
      "low": 393.0,
      "volume": 1710429
    },
    {
      "date": "2022-03-09",
      "price": 402.4,
      "high": 404.1,
      "low": 385.5,
      "volume": 1418960
    },
    {
      "date": "2022-03-11",
      "price": 411.6,
      "high": 423.9,
      "low": 410.2,
      "volume": 786654
    },
    {
      "date": "2022-03-15",
      "price": 427.8,
      "high": 430.7,
      "low": 421.6,
      "volume": 665639
    },
    {
      "date": "2022-03-17",
      "price": 437.1,
      "high": 440.9,
      "low": 434.0,
      "volume": 746578
    },
    {
      "date": "2022-03-21",
      "price": 451.6,
      "high": 452.3,
      "low": 436.0,
      "volume": 860538
    },
    {
      "date": "2022-03-23",
      "price": 447.5,
      "high": 463.2,
      "low": 447.5,
      "volume": 853307
    },
    {
      "date": "2022-03-25",
      "price": 446.8,
      "high": 450.6,
      "low": 445.8,
      "volume": 473963
    },
    {
      "date": "2022-03-29",
      "price": 452.9,
      "high": 457.1,
      "low": 438.1,
      "volume": 877353
    },
    {
      "date": "2022-03-31",
      "price": 442.0,
      "high": 464.5,
      "low": 441.5,
      "volume": 1305962
    },
    {
      "date": "2022-04-04",
      "price": 457.1,
      "high": 460.7,
      "low": 452.5,
      "volume": 553230
    },
    {
      "date": "2022-04-06",
      "price": 469.9,
      "high": 473.9,
      "low": 465.6,
      "volume": 627712
    },
    {
      "date": "2022-04-08",
      "price": 485.6,
      "high": 492.7,
      "low": 472.9,
      "volume": 884515
    },
    {
      "date": "2022-04-12",
      "price": 486.3,
      "high": 496.5,
      "low": 486.3,
      "volume": 851621
    },
    {
      "date": "2022-04-19",
      "price": 489.4,
      "high": 499.0,
      "low": 488.7,
      "volume": 782280
    },
    {
      "date": "2022-04-21",
      "price": 492.9,
      "high": 496.8,
      "low": 483.1,
      "volume": 530580
    },
    {
      "date": "2022-04-25",
      "price": 462.5,
      "high": 472.0,
      "low": 461.2,
      "volume": 722527
    },
    {
      "date": "2022-04-27",
      "price": 458.6,
      "high": 479.7,
      "low": 449.0,
      "volume": 1205571
    },
    {
      "date": "2022-04-29",
      "price": 480.7,
      "high": 485.3,
      "low": 467.0,
      "volume": 931020
    },
    {
      "date": "2022-05-03",
      "price": 485.8,
      "high": 485.8,
      "low": 473.3,
      "volume": 724820
    },
    {
      "date": "2022-05-05",
      "price": 488.2,
      "high": 501.2,
      "low": 485.3,
      "volume": 511582
    },
    {
      "date": "2022-05-09",
      "price": 465.8,
      "high": 474.6,
      "low": 462.3,
      "volume": 529529
    },
    {
      "date": "2022-05-11",
      "price": 445.9,
      "high": 448.2,
      "low": 437.0,
      "volume": 967859
    },
    {
      "date": "2022-05-13",
      "price": 463.2,
      "high": 464.2,
      "low": 440.9,
      "volume": 701588
    },
    {
      "date": "2022-05-18",
      "price": 473.4,
      "high": 475.4,
      "low": 467.3,
      "volume": 756957
    },
    {
      "date": "2022-05-20",
      "price": 473.3,
      "high": 477.6,
      "low": 468.8,
      "volume": 455358
    },
    {
      "date": "2022-05-24",
      "price": 481.2,
      "high": 491.6,
      "low": 474.8,
      "volume": 767224
    },
    {
      "date": "2022-05-27",
      "price": 483.8,
      "high": 491.6,
      "low": 476.2,
      "volume": 774328
    },
    {
      "date": "2022-05-31",
      "price": 485.6,
      "high": 489.5,
      "low": 476.4,
      "volume": 1195656
    },
    {
      "date": "2022-06-02",
      "price": 494.0,
      "high": 494.3,
      "low": 484.7,
      "volume": 557975
    },
    {
      "date": "2022-06-07",
      "price": 486.8,
      "high": 498.9,
      "low": 484.2,
      "volume": 657739
    },
    {
      "date": "2022-06-09",
      "price": 479.6,
      "high": 490.7,
      "low": 475.6,
      "volume": 851506
    },
    {
      "date": "2022-06-13",
      "price": 459.7,
      "high": 471.2,
      "low": 459.7,
      "volume": 611565
    },
    {
      "date": "2022-06-15",
      "price": 466.3,
      "high": 478.4,
      "low": 466.3,
      "volume": 899780
    },
    {
      "date": "2022-06-17",
      "price": 441.5,
      "high": 455.2,
      "low": 440.8,
      "volume": 1360547
    },
    {
      "date": "2022-06-21",
      "price": 452.1,
      "high": 460.0,
      "low": 449.7,
      "volume": 537811
    },
    {
      "date": "2022-06-23",
      "price": 427.9,
      "high": 441.9,
      "low": 425.5,
      "volume": 1099108
    },
    {
      "date": "2022-06-27",
      "price": 432.3,
      "high": 436.6,
      "low": 425.2,
      "volume": 743332
    },
    {
      "date": "2022-06-29",
      "price": 440.2,
      "high": 452.2,
      "low": 440.2,
      "volume": 751393
    },
    {
      "date": "2022-07-01",
      "price": 416.3,
      "high": 425.0,
      "low": 410.8,
      "volume": 786349
    },
    {
      "date": "2022-07-05",
      "price": 398.5,
      "high": 422.2,
      "low": 396.5,
      "volume": 1058051
    },
    {
      "date": "2022-07-07",
      "price": 411.5,
      "high": 416.4,
      "low": 401.8,
      "volume": 454603
    },
    {
      "date": "2022-07-11",
      "price": 406.7,
      "high": 415.3,
      "low": 396.8,
      "volume": 650509
    },
    {
      "date": "2022-07-13",
      "price": 399.3,
      "high": 411.0,
      "low": 399.1,
      "volume": 799450
    },
    {
      "date": "2022-07-15",
      "price": 410.1,
      "high": 410.1,
      "low": 393.9,
      "volume": 716498
    },
    {
      "date": "2022-07-19",
      "price": 416.4,
      "high": 416.4,
      "low": 402.1,
      "volume": 1181545
    },
    {
      "date": "2022-07-21",
      "price": 410.8,
      "high": 414.7,
      "low": 407.8,
      "volume": 527359
    },
    {
      "date": "2022-07-25",
      "price": 408.4,
      "high": 409.1,
      "low": 402.7,
      "volume": 465007
    },
    {
      "date": "2022-07-27",
      "price": 402.5,
      "high": 412.4,
      "low": 402.0,
      "volume": 423672
    },
    {
      "date": "2022-07-29",
      "price": 411.0,
      "high": 412.8,
      "low": 406.9,
      "volume": 574943
    },
    {
      "date": "2022-08-02",
      "price": 412.7,
      "high": 414.4,
      "low": 403.5,
      "volume": 445531
    },
    {
      "date": "2022-08-04",
      "price": 411.9,
      "high": 419.3,
      "low": 411.8,
      "volume": 414263
    },
    {
      "date": "2022-08-08",
      "price": 417.3,
      "high": 421.5,
      "low": 414.3,
      "volume": 369686
    },
    {
      "date": "2022-08-10",
      "price": 417.6,
      "high": 420.5,
      "low": 414.0,
      "volume": 468280
    },
    {
      "date": "2022-08-12",
      "price": 424.5,
      "high": 425.4,
      "low": 419.1,
      "volume": 377442
    },
    {
      "date": "2022-08-16",
      "price": 423.3,
      "high": 428.5,
      "low": 420.6,
      "volume": 353971
    },
    {
      "date": "2022-08-18",
      "price": 428.5,
      "high": 429.2,
      "low": 421.6,
      "volume": 362629
    },
    {
      "date": "2022-08-22",
      "price": 405.5,
      "high": 419.0,
      "low": 403.6,
      "volume": 566284
    },
    {
      "date": "2022-08-24",
      "price": 406.5,
      "high": 418.7,
      "low": 404.7,
      "volume": 712836
    },
    {
      "date": "2022-08-26",
      "price": 416.0,
      "high": 424.0,
      "low": 415.3,
      "volume": 412852
    },
    {
      "date": "2022-08-30",
      "price": 415.8,
      "high": 427.2,
      "low": 415.8,
      "volume": 602451
    },
    {
      "date": "2022-09-01",
      "price": 415.4,
      "high": 418.6,
      "low": 412.6,
      "volume": 350095
    },
    {
      "date": "2022-09-05",
      "price": 403.0,
      "high": 410.3,
      "low": 396.0,
      "volume": 789557
    },
    {
      "date": "2022-09-07",
      "price": 402.5,
      "high": 402.5,
      "low": 388.2,
      "volume": 813407
    },
    {
      "date": "2022-09-09",
      "price": 416.2,
      "high": 416.2,
      "low": 397.0,
      "volume": 647678
    },
    {
      "date": "2022-09-13",
      "price": 420.3,
      "high": 425.6,
      "low": 414.6,
      "volume": 559439
    },
    {
      "date": "2022-09-15",
      "price": 419.6,
      "high": 420.8,
      "low": 414.8,
      "volume": 403418
    },
    {
      "date": "2022-09-19",
      "price": 408.3,
      "high": 409.0,
      "low": 395.5,
      "volume": 585973
    },
    {
      "date": "2022-09-21",
      "price": 401.0,
      "high": 411.3,
      "low": 401.0,
      "volume": 624035
    },
    {
      "date": "2022-09-23",
      "price": 385.1,
      "high": 406.9,
      "low": 385.1,
      "volume": 831557
    },
    {
      "date": "2022-09-27",
      "price": 393.8,
      "high": 393.8,
      "low": 385.0,
      "volume": 459892
    },
    {
      "date": "2022-09-29",
      "price": 376.9,
      "high": 384.6,
      "low": 375.8,
      "volume": 589028
    },
    {
      "date": "2022-10-03",
      "price": 389.7,
      "high": 392.8,
      "low": 380.0,
      "volume": 493441
    },
    {
      "date": "2022-10-05",
      "price": 390.9,
      "high": 397.0,
      "low": 386.0,
      "volume": 680676
    },
    {
      "date": "2022-10-07",
      "price": 412.0,
      "high": 412.0,
      "low": 392.8,
      "volume": 1170148
    },
    {
      "date": "2022-10-11",
      "price": 410.7,
      "high": 419.7,
      "low": 408.0,
      "volume": 440466
    },
    {
      "date": "2022-10-13",
      "price": 416.1,
      "high": 421.5,
      "low": 406.7,
      "volume": 564651
    },
    {
      "date": "2022-10-17",
      "price": 408.8,
      "high": 411.3,
      "low": 402.8,
      "volume": 460679
    },
    {
      "date": "2022-10-19",
      "price": 426.6,
      "high": 427.9,
      "low": 419.8,
      "volume": 494932
    },
    {
      "date": "2022-10-21",
      "price": 456.7,
      "high": 458.2,
      "low": 446.6,
      "volume": 631831
    },
    {
      "date": "2022-10-25",
      "price": 457.4,
      "high": 472.4,
      "low": 451.2,
      "volume": 594104
    },
    {
      "date": "2022-10-27",
      "price": 461.1,
      "high": 467.0,
      "low": 456.7,
      "volume": 269397
    },
    {
      "date": "2022-10-31",
      "price": 464.0,
      "high": 469.1,
      "low": 458.5,
      "volume": 399173
    },
    {
      "date": "2022-11-02",
      "price": 459.5,
      "high": 464.2,
      "low": 452.3,
      "volume": 464156
    },
    {
      "date": "2022-11-04",
      "price": 463.0,
      "high": 467.3,
      "low": 458.2,
      "volume": 339335
    },
    {
      "date": "2022-11-08",
      "price": 466.5,
      "high": 467.8,
      "low": 458.0,
      "volume": 325831
    },
    {
      "date": "2022-11-10",
      "price": 464.2,
      "high": 470.1,
      "low": 461.1,
      "volume": 491183
    },
    {
      "date": "2022-11-14",
      "price": 464.5,
      "high": 469.2,
      "low": 462.8,
      "volume": 411378
    },
    {
      "date": "2022-11-16",
      "price": 461.7,
      "high": 469.8,
      "low": 460.0,
      "volume": 431049
    },
    {
      "date": "2022-11-18",
      "price": 457.8,
      "high": 459.7,
      "low": 453.0,
      "volume": 320532
    },
    {
      "date": "2022-11-22",
      "price": 461.4,
      "high": 462.0,
      "low": 453.0,
      "volume": 325975
    },
    {
      "date": "2022-11-24",
      "price": 464.6,
      "high": 465.9,
      "low": 458.0,
      "volume": 227330
    },
    {
      "date": "2022-11-28",
      "price": 466.3,
      "high": 469.0,
      "low": 462.4,
      "volume": 361872
    },
    {
      "date": "2022-11-30",
      "price": 450.0,
      "high": 465.4,
      "low": 449.1,
      "volume": 1006363
    },
    {
      "date": "2022-12-02",
      "price": 450.5,
      "high": 450.5,
      "low": 441.6,
      "volume": 473380
    },
    {
      "date": "2022-12-06",
      "price": 442.2,
      "high": 452.2,
      "low": 447.2,
      "volume": 361806
    },
    {
      "date": "2022-12-08",
      "price": 427.2,
      "high": 435.0,
      "low": 425.9,
      "volume": 622316
    },
    {
      "date": "2022-12-12",
      "price": 428.0,
      "high": 432.3,
      "low": 424.9,
      "volume": 367739
    },
    {
      "date": "2022-12-14",
      "price": 431.7,
      "high": 435.6,
      "low": 429.0,
      "volume": 393695
    },
    {
      "date": "2022-12-16",
      "price": 424.7,
      "high": 429.2,
      "low": 420.4,
      "volume": 936974
    },
    {
      "date": "2022-12-20",
      "price": 422.6,
      "high": 425.4,
      "low": 417.2,
      "volume": 568509
    },
    {
      "date": "2022-12-22",
      "price": 425.9,
      "high": 432.9,
      "low": 424.8,
      "volume": 313905
    },
    {
      "date": "2022-12-27",
      "price": 431.4,
      "high": 434.3,
      "low": 430.1,
      "volume": 155910
    },
    {
      "date": "2022-12-29",
      "price": 431.9,
      "high": 433.0,
      "low": 426.4,
      "volume": 205122
    },
    {
      "date": "2023-01-02",
      "price": 437.6,
      "high": 438.7,
      "low": 432.2,
      "volume": 222982
    },
    {
      "date": "2023-01-04",
      "price": 438.3,
      "high": 439.5,
      "low": 427.2,
      "volume": 549083
    },
    {
      "date": "2023-01-06",
      "price": 458.1,
      "high": 460.0,
      "low": 447.6,
      "volume": 466647
    },
    {
      "date": "2023-01-10",
      "price": 455.6,
      "high": 463.2,
      "low": 454.4,
      "volume": 418617
    },
    {
      "date": "2023-01-12",
      "price": 456.5,
      "high": 458.9,
      "low": 454.2,
      "volume": 294871
    },
    {
      "date": "2023-01-16",
      "price": 452.3,
      "high": 457.2,
      "low": 451.7,
      "volume": 202089
    },
    {
      "date": "2023-01-18",
      "price": 455.9,
      "high": 458.9,
      "low": 450.6,
      "volume": 339139
    },
    {
      "date": "2023-01-20",
      "price": 442.6,
      "high": 447.8,
      "low": 440.7,
      "volume": 407215
    },
    {
      "date": "2023-01-24",
      "price": 444.6,
      "high": 449.2,
      "low": 441.5,
      "volume": 378415
    },
    {
      "date": "2023-01-26",
      "price": 446.6,
      "high": 448.3,
      "low": 443.3,
      "volume": 308404
    },
    {
      "date": "2023-01-30",
      "price": 443.3,
      "high": 448.5,
      "low": 443.3,
      "volume": 443446
    },
    {
      "date": "2023-02-01",
      "price": 443.1,
      "high": 448.0,
      "low": 442.3,
      "volume": 451629
    },
    {
      "date": "2023-02-03",
      "price": 454.9,
      "high": 455.6,
      "low": 444.2,
      "volume": 486162
    },
    {
      "date": "2023-02-07",
      "price": 446.0,
      "high": 451.4,
      "low": 442.7,
      "volume": 476104
    },
    {
      "date": "2023-02-09",
      "price": 464.5,
      "high": 473.0,
      "low": 463.2,
      "volume": 536022
    },
    {
      "date": "2023-02-13",
      "price": 462.3,
      "high": 465.5,
      "low": 455.5,
      "volume": 506259
    },
    {
      "date": "2023-02-15",
      "price": 466.5,
      "high": 466.5,
      "low": 461.0,
      "volume": 503241
    },
    {
      "date": "2023-02-17",
      "price": 464.2,
      "high": 467.7,
      "low": 460.6,
      "volume": 533270
    },
    {
      "date": "2023-02-21",
      "price": 467.0,
      "high": 470.9,
      "low": 466.6,
      "volume": 346640
    },
    {
      "date": "2023-02-23",
      "price": 479.9,
      "high": 483.6,
      "low": 478.4,
      "volume": 506189
    },
    {
      "date": "2023-02-27",
      "price": 483.1,
      "high": 489.0,
      "low": 482.5,
      "volume": 537450
    },
    {
      "date": "2023-03-01",
      "price": 491.8,
      "high": 497.0,
      "low": 486.9,
      "volume": 727773
    },
    {
      "date": "2023-03-03",
      "price": 493.9,
      "high": 497.4,
      "low": 489.5,
      "volume": 480899
    },
    {
      "date": "2023-03-07",
      "price": 483.2,
      "high": 489.9,
      "low": 482.2,
      "volume": 555144
    },
    {
      "date": "2023-03-09",
      "price": 492.2,
      "high": 495.6,
      "low": 488.9,
      "volume": 459827
    },
    {
      "date": "2023-03-13",
      "price": 463.3,
      "high": 476.5,
      "low": 462.5,
      "volume": 837716
    },
    {
      "date": "2023-03-15",
      "price": 456.1,
      "high": 471.1,
      "low": 455.2,
      "volume": 649883
    },
    {
      "date": "2023-03-17",
      "price": 444.3,
      "high": 463.3,
      "low": 442.5,
      "volume": 4813431
    },
    {
      "date": "2023-03-21",
      "price": 456.3,
      "high": 460.4,
      "low": 449.7,
      "volume": 554729
    },
    {
      "date": "2023-03-23",
      "price": 452.5,
      "high": 455.8,
      "low": 449.3,
      "volume": 518294
    },
    {
      "date": "2023-03-27",
      "price": 441.8,
      "high": 446.2,
      "low": 437.1,
      "volume": 421018
    },
    {
      "date": "2023-03-29",
      "price": 451.3,
      "high": 451.4,
      "low": 446.0,
      "volume": 365633
    },
    {
      "date": "2023-03-31",
      "price": 453.9,
      "high": 462.4,
      "low": 451.6,
      "volume": 582500
    },
    {
      "date": "2023-04-04",
      "price": 451.3,
      "high": 455.5,
      "low": 451.2,
      "volume": 310151
    },
    {
      "date": "2023-04-11",
      "price": 459.5,
      "high": 459.5,
      "low": 449.7,
      "volume": 597056
    },
    {
      "date": "2023-04-13",
      "price": 453.4,
      "high": 461.4,
      "low": 452.0,
      "volume": 536864
    },
    {
      "date": "2023-04-17",
      "price": 462.7,
      "high": 465.0,
      "low": 457.9,
      "volume": 419648
    },
    {
      "date": "2023-04-19",
      "price": 454.9,
      "high": 459.2,
      "low": 453.2,
      "volume": 654391
    },
    {
      "date": "2023-04-21",
      "price": 455.0,
      "high": 460.7,
      "low": 453.2,
      "volume": 338927
    },
    {
      "date": "2023-04-25",
      "price": 443.4,
      "high": 450.8,
      "low": 439.5,
      "volume": 822808
    },
    {
      "date": "2023-04-27",
      "price": 448.4,
      "high": 449.5,
      "low": 445.1,
      "volume": 458066
    },
    {
      "date": "2023-05-02",
      "price": 429.3,
      "high": 437.3,
      "low": 428.1,
      "volume": 723433
    },
    {
      "date": "2023-05-04",
      "price": 427.0,
      "high": 431.9,
      "low": 426.5,
      "volume": 550342
    },
    {
      "date": "2023-05-08",
      "price": 429.6,
      "high": 434.0,
      "low": 429.0,
      "volume": 356000
    },
    {
      "date": "2023-05-10",
      "price": 418.8,
      "high": 425.2,
      "low": 417.9,
      "volume": 562227
    },
    {
      "date": "2023-05-12",
      "price": 420.1,
      "high": 420.3,
      "low": 414.5,
      "volume": 520007
    },
    {
      "date": "2023-05-16",
      "price": 422.0,
      "high": 425.0,
      "low": 420.7,
      "volume": 356310
    },
    {
      "date": "2023-05-22",
      "price": 423.4,
      "high": 425.6,
      "low": 421.8,
      "volume": 338691
    },
    {
      "date": "2023-05-24",
      "price": 424.4,
      "high": 427.7,
      "low": 423.0,
      "volume": 418385
    },
    {
      "date": "2023-05-26",
      "price": 425.1,
      "high": 426.2,
      "low": 424.4,
      "volume": 421877
    },
    {
      "date": "2023-05-31",
      "price": 414.2,
      "high": 425.3,
      "low": 414.2,
      "volume": 1494145
    },
    {
      "date": "2023-06-02",
      "price": 422.6,
      "high": 423.5,
      "low": 416.0,
      "volume": 572636
    },
    {
      "date": "2023-06-06",
      "price": 419.5,
      "high": 423.7,
      "low": 417.6,
      "volume": 419915
    },
    {
      "date": "2023-06-08",
      "price": 425.6,
      "high": 429.7,
      "low": 424.4,
      "volume": 656931
    },
    {
      "date": "2023-06-12",
      "price": 378.0,
      "high": 433.2,
      "low": 427.6,
      "volume": 975197
    },
    {
      "date": "2023-06-14",
      "price": 366.8,
      "high": 382.2,
      "low": 365.0,
      "volume": 1447516
    },
    {
      "date": "2023-06-16",
      "price": 376.5,
      "high": 379.8,
      "low": 369.4,
      "volume": 1535379
    },
    {
      "date": "2023-06-20",
      "price": 368.0,
      "high": 373.1,
      "low": 367.2,
      "volume": 658603
    },
    {
      "date": "2023-06-22",
      "price": 372.0,
      "high": 375.0,
      "low": 369.0,
      "volume": 691508
    },
    {
      "date": "2023-06-26",
      "price": 377.4,
      "high": 379.3,
      "low": 367.8,
      "volume": 754008
    },
    {
      "date": "2023-06-28",
      "price": 370.2,
      "high": 372.9,
      "low": 367.8,
      "volume": 552039
    },
    {
      "date": "2023-06-30",
      "price": 379.0,
      "high": 381.3,
      "low": 377.0,
      "volume": 611623
    },
    {
      "date": "2023-07-04",
      "price": 384.4,
      "high": 385.0,
      "low": 379.3,
      "volume": 296729
    },
    {
      "date": "2023-07-06",
      "price": 381.7,
      "high": 383.8,
      "low": 378.6,
      "volume": 596825
    },
    {
      "date": "2023-07-10",
      "price": 389.1,
      "high": 389.1,
      "low": 382.0,
      "volume": 512945
    },
    {
      "date": "2023-07-12",
      "price": 391.5,
      "high": 393.2,
      "low": 389.1,
      "volume": 349194
    },
    {
      "date": "2023-07-14",
      "price": 388.3,
      "high": 390.0,
      "low": 386.7,
      "volume": 385174
    },
    {
      "date": "2023-07-18",
      "price": 395.0,
      "high": 395.0,
      "low": 381.0,
      "volume": 650779
    },
    {
      "date": "2023-07-20",
      "price": 403.3,
      "high": 406.3,
      "low": 389.4,
      "volume": 1003574
    },
    {
      "date": "2023-07-24",
      "price": 407.8,
      "high": 408.7,
      "low": 401.7,
      "volume": 244671
    },
    {
      "date": "2023-07-26",
      "price": 410.6,
      "high": 413.4,
      "low": 408.7,
      "volume": 389012
    },
    {
      "date": "2023-07-28",
      "price": 414.4,
      "high": 415.3,
      "low": 412.1,
      "volume": 211077
    },
    {
      "date": "2023-08-01",
      "price": 412.3,
      "high": 416.7,
      "low": 412.3,
      "volume": 202442
    },
    {
      "date": "2023-08-03",
      "price": 407.6,
      "high": 409.6,
      "low": 403.3,
      "volume": 208010
    },
    {
      "date": "2023-08-07",
      "price": 412.2,
      "high": 417.9,
      "low": 411.1,
      "volume": 213356
    },
    {
      "date": "2023-08-09",
      "price": 406.9,
      "high": 411.2,
      "low": 402.1,
      "volume": 718581
    },
    {
      "date": "2023-08-11",
      "price": 400.8,
      "high": 405.2,
      "low": 397.1,
      "volume": 499987
    },
    {
      "date": "2023-08-15",
      "price": 392.9,
      "high": 400.3,
      "low": 391.7,
      "volume": 578976
    },
    {
      "date": "2023-08-17",
      "price": 394.3,
      "high": 394.7,
      "low": 391.7,
      "volume": 270790
    },
    {
      "date": "2023-08-21",
      "price": 388.6,
      "high": 393.4,
      "low": 387.5,
      "volume": 348765
    },
    {
      "date": "2023-08-23",
      "price": 383.1,
      "high": 392.6,
      "low": 381.6,
      "volume": 568645
    },
    {
      "date": "2023-08-25",
      "price": 381.6,
      "high": 383.8,
      "low": 378.8,
      "volume": 232516
    },
    {
      "date": "2023-08-29",
      "price": 386.4,
      "high": 388.1,
      "low": 384.5,
      "volume": 373774
    },
    {
      "date": "2023-08-31",
      "price": 388.9,
      "high": 391.6,
      "low": 388.9,
      "volume": 572578
    },
    {
      "date": "2023-09-04",
      "price": 405.0,
      "high": 405.0,
      "low": 388.8,
      "volume": 1079040
    },
    {
      "date": "2023-09-06",
      "price": 408.4,
      "high": 411.8,
      "low": 406.1,
      "volume": 508024
    },
    {
      "date": "2023-09-08",
      "price": 409.5,
      "high": 412.5,
      "low": 407.4,
      "volume": 307791
    },
    {
      "date": "2023-09-12",
      "price": 409.5,
      "high": 414.9,
      "low": 408.3,
      "volume": 367204
    },
    {
      "date": "2023-09-14",
      "price": 415.3,
      "high": 417.1,
      "low": 409.7,
      "volume": 498690
    },
    {
      "date": "2023-09-18",
      "price": 405.3,
      "high": 410.9,
      "low": 403.7,
      "volume": 431224
    },
    {
      "date": "2023-09-20",
      "price": 406.4,
      "high": 409.9,
      "low": 402.3,
      "volume": 580142
    },
    {
      "date": "2023-09-22",
      "price": 407.5,
      "high": 410.7,
      "low": 405.7,
      "volume": 421567
    },
    {
      "date": "2023-09-26",
      "price": 402.3,
      "high": 407.5,
      "low": 402.1,
      "volume": 350343
    },
    {
      "date": "2023-09-28",
      "price": 401.7,
      "high": 404.5,
      "low": 398.3,
      "volume": 333112
    },
    {
      "date": "2023-10-02",
      "price": 400.2,
      "high": 408.8,
      "low": 399.9,
      "volume": 479840
    },
    {
      "date": "2023-10-04",
      "price": 392.5,
      "high": 399.9,
      "low": 391.5,
      "volume": 305096
    },
    {
      "date": "2023-10-06",
      "price": 390.0,
      "high": 397.2,
      "low": 389.3,
      "volume": 360058
    },
    {
      "date": "2023-10-10",
      "price": 401.6,
      "high": 403.5,
      "low": 397.4,
      "volume": 470429
    },
    {
      "date": "2023-10-12",
      "price": 398.7,
      "high": 402.5,
      "low": 397.1,
      "volume": 256489
    },
    {
      "date": "2023-10-16",
      "price": 394.5,
      "high": 404.8,
      "low": 392.7,
      "volume": 471041
    },
    {
      "date": "2023-10-18",
      "price": 387.9,
      "high": 393.4,
      "low": 387.4,
      "volume": 415764
    },
    {
      "date": "2023-10-20",
      "price": 361.6,
      "high": 371.1,
      "low": 358.3,
      "volume": 1527502
    },
    {
      "date": "2023-10-24",
      "price": 361.7,
      "high": 363.7,
      "low": 358.0,
      "volume": 375406
    },
    {
      "date": "2023-10-26",
      "price": 356.7,
      "high": 361.1,
      "low": 354.3,
      "volume": 571587
    },
    {
      "date": "2023-10-30",
      "price": 364.5,
      "high": 366.5,
      "low": 359.0,
      "volume": 454724
    },
    {
      "date": "2023-11-01",
      "price": 363.2,
      "high": 367.4,
      "low": 362.9,
      "volume": 283092
    },
    {
      "date": "2023-11-03",
      "price": 368.2,
      "high": 370.9,
      "low": 367.1,
      "volume": 249227
    },
    {
      "date": "2023-11-07",
      "price": 359.7,
      "high": 366.5,
      "low": 359.7,
      "volume": 416751
    },
    {
      "date": "2023-11-09",
      "price": 371.4,
      "high": 374.0,
      "low": 366.9,
      "volume": 392440
    },
    {
      "date": "2023-11-13",
      "price": 363.3,
      "high": 366.7,
      "low": 363.0,
      "volume": 312517
    },
    {
      "date": "2023-11-15",
      "price": 377.7,
      "high": 379.5,
      "low": 371.7,
      "volume": 759775
    },
    {
      "date": "2023-11-17",
      "price": 373.1,
      "high": 376.0,
      "low": 371.4,
      "volume": 624243
    },
    {
      "date": "2023-11-21",
      "price": 366.9,
      "high": 372.2,
      "low": 365.6,
      "volume": 328892
    },
    {
      "date": "2023-11-23",
      "price": 366.7,
      "high": 366.8,
      "low": 363.6,
      "volume": 301582
    },
    {
      "date": "2023-11-27",
      "price": 370.4,
      "high": 373.8,
      "low": 369.2,
      "volume": 377640
    },
    {
      "date": "2023-11-29",
      "price": 361.9,
      "high": 365.4,
      "low": 361.8,
      "volume": 460578
    },
    {
      "date": "2023-12-01",
      "price": 362.6,
      "high": 367.7,
      "low": 359.9,
      "volume": 469933
    },
    {
      "date": "2023-12-05",
      "price": 359.5,
      "high": 363.0,
      "low": 359.3,
      "volume": 317516
    },
    {
      "date": "2023-12-07",
      "price": 359.1,
      "high": 359.3,
      "low": 354.5,
      "volume": 328971
    },
    {
      "date": "2023-12-11",
      "price": 362.9,
      "high": 362.9,
      "low": 360.4,
      "volume": 389613
    },
    {
      "date": "2023-12-13",
      "price": 362.7,
      "high": 364.8,
      "low": 360.3,
      "volume": 519131
    },
    {
      "date": "2023-12-15",
      "price": 364.3,
      "high": 369.9,
      "low": 364.3,
      "volume": 1269172
    },
    {
      "date": "2023-12-19",
      "price": 366.6,
      "high": 366.9,
      "low": 361.7,
      "volume": 440788
    },
    {
      "date": "2023-12-21",
      "price": 361.3,
      "high": 364.6,
      "low": 359.8,
      "volume": 438544
    },
    {
      "date": "2023-12-27",
      "price": 364.3,
      "high": 365.8,
      "low": 360.7,
      "volume": 285623
    },
    {
      "date": "2023-12-29",
      "price": 361.2,
      "high": 364.1,
      "low": 361.2,
      "volume": 304150
    },
    {
      "date": "2024-01-03",
      "price": 364.3,
      "high": 365.1,
      "low": 360.6,
      "volume": 277056
    },
    {
      "date": "2024-01-05",
      "price": 351.6,
      "high": 365.7,
      "low": 348.7,
      "volume": 1292777
    },
    {
      "date": "2024-01-09",
      "price": 352.5,
      "high": 354.1,
      "low": 345.1,
      "volume": 599713
    },
    {
      "date": "2024-01-11",
      "price": 351.3,
      "high": 354.0,
      "low": 350.0,
      "volume": 608285
    },
    {
      "date": "2024-01-15",
      "price": 342.6,
      "high": 343.8,
      "low": 341.4,
      "volume": 387895
    },
    {
      "date": "2024-01-17",
      "price": 344.2,
      "high": 346.6,
      "low": 342.0,
      "volume": 899026
    },
    {
      "date": "2024-01-19",
      "price": 340.0,
      "high": 348.5,
      "low": 340.0,
      "volume": 618873
    },
    {
      "date": "2024-01-23",
      "price": 341.3,
      "high": 342.4,
      "low": 336.4,
      "volume": 556496
    },
    {
      "date": "2024-01-25",
      "price": 344.6,
      "high": 348.0,
      "low": 342.9,
      "volume": 400317
    },
    {
      "date": "2024-01-29",
      "price": 353.1,
      "high": 355.9,
      "low": 351.3,
      "volume": 506658
    },
    {
      "date": "2024-01-31",
      "price": 349.4,
      "high": 351.3,
      "low": 347.8,
      "volume": 514848
    },
    {
      "date": "2024-02-02",
      "price": 352.6,
      "high": 356.6,
      "low": 351.9,
      "volume": 430667
    },
    {
      "date": "2024-02-06",
      "price": 352.2,
      "high": 354.7,
      "low": 350.0,
      "volume": 393015
    },
    {
      "date": "2024-02-08",
      "price": 344.3,
      "high": 348.8,
      "low": 344.0,
      "volume": 537427
    },
    {
      "date": "2024-02-12",
      "price": 363.8,
      "high": 365.6,
      "low": 356.8,
      "volume": 803564
    },
    {
      "date": "2024-02-14",
      "price": 360.3,
      "high": 362.9,
      "low": 351.5,
      "volume": 959657
    },
    {
      "date": "2024-02-16",
      "price": 355.0,
      "high": 358.1,
      "low": 353.2,
      "volume": 586629
    },
    {
      "date": "2024-02-20",
      "price": 351.2,
      "high": 355.6,
      "low": 350.9,
      "volume": 533113
    },
    {
      "date": "2024-02-22",
      "price": 345.3,
      "high": 348.1,
      "low": 343.7,
      "volume": 485926
    },
    {
      "date": "2024-02-26",
      "price": 343.0,
      "high": 345.8,
      "low": 340.9,
      "volume": 439603
    },
    {
      "date": "2024-02-28",
      "price": 332.0,
      "high": 336.0,
      "low": 330.5,
      "volume": 880082
    },
    {
      "date": "2024-03-01",
      "price": 342.3,
      "high": 344.0,
      "low": 331.2,
      "volume": 804715
    },
    {
      "date": "2024-03-05",
      "price": 336.1,
      "high": 339.5,
      "low": 334.4,
      "volume": 579294
    },
    {
      "date": "2024-03-07",
      "price": 327.8,
      "high": 333.3,
      "low": 327.8,
      "volume": 765778
    },
    {
      "date": "2024-03-11",
      "price": 328.0,
      "high": 330.2,
      "low": 325.3,
      "volume": 592002
    },
    {
      "date": "2024-03-13",
      "price": 330.4,
      "high": 330.4,
      "low": 323.1,
      "volume": 873234
    },
    {
      "date": "2024-03-15",
      "price": 334.2,
      "high": 334.4,
      "low": 326.0,
      "volume": 3736440
    },
    {
      "date": "2024-03-19",
      "price": 340.5,
      "high": 342.5,
      "low": 336.4,
      "volume": 665024
    },
    {
      "date": "2024-03-21",
      "price": 338.8,
      "high": 341.3,
      "low": 336.9,
      "volume": 433567
    },
    {
      "date": "2024-03-25",
      "price": 337.6,
      "high": 343.9,
      "low": 337.3,
      "volume": 513101
    },
    {
      "date": "2024-03-27",
      "price": 342.9,
      "high": 343.2,
      "low": 336.8,
      "volume": 449191
    },
    {
      "date": "2024-04-03",
      "price": 353.2,
      "high": 353.8,
      "low": 342.8,
      "volume": 706639
    },
    {
      "date": "2024-04-05",
      "price": 351.4,
      "high": 360.3,
      "low": 351.1,
      "volume": 518635
    },
    {
      "date": "2024-04-09",
      "price": 334.4,
      "high": 341.8,
      "low": 331.3,
      "volume": 1897230
    },
    {
      "date": "2024-04-11",
      "price": 334.3,
      "high": 338.4,
      "low": 333.8,
      "volume": 828752
    },
    {
      "date": "2024-04-15",
      "price": 334.0,
      "high": 336.0,
      "low": 330.5,
      "volume": 598635
    },
    {
      "date": "2024-04-17",
      "price": 328.0,
      "high": 333.7,
      "low": 326.5,
      "volume": 694727
    },
    {
      "date": "2024-04-19",
      "price": 337.3,
      "high": 338.6,
      "low": 331.8,
      "volume": 834177
    },
    {
      "date": "2024-04-23",
      "price": 339.8,
      "high": 341.4,
      "low": 337.8,
      "volume": 584162
    },
    {
      "date": "2024-04-25",
      "price": 339.9,
      "high": 342.1,
      "low": 332.1,
      "volume": 864940
    },
    {
      "date": "2024-04-29",
      "price": 316.6,
      "high": 317.0,
      "low": 310.5,
      "volume": 1372253
    },
    {
      "date": "2024-05-02",
      "price": 313.2,
      "high": 316.1,
      "low": 310.2,
      "volume": 792671
    },
    {
      "date": "2024-05-06",
      "price": 319.1,
      "high": 320.0,
      "low": 315.8,
      "volume": 592803
    },
    {
      "date": "2024-05-08",
      "price": 317.4,
      "high": 323.5,
      "low": 316.3,
      "volume": 714884
    },
    {
      "date": "2024-05-13",
      "price": 314.3,
      "high": 316.1,
      "low": 311.0,
      "volume": 1152607
    },
    {
      "date": "2024-05-15",
      "price": 318.6,
      "high": 320.1,
      "low": 316.6,
      "volume": 565528
    },
    {
      "date": "2024-05-21",
      "price": 327.0,
      "high": 329.1,
      "low": 323.1,
      "volume": 884467
    },
    {
      "date": "2024-05-23",
      "price": 325.8,
      "high": 329.8,
      "low": 325.8,
      "volume": 370212
    },
    {
      "date": "2024-05-27",
      "price": 331.9,
      "high": 331.9,
      "low": 327.8,
      "volume": 380462
    },
    {
      "date": "2024-05-29",
      "price": 325.0,
      "high": 330.1,
      "low": 324.0,
      "volume": 585536
    },
    {
      "date": "2024-05-31",
      "price": 324.9,
      "high": 328.3,
      "low": 322.4,
      "volume": 1696719
    },
    {
      "date": "2024-06-04",
      "price": 325.4,
      "high": 325.5,
      "low": 318.7,
      "volume": 814125
    },
    {
      "date": "2024-06-06",
      "price": 312.1,
      "high": 314.4,
      "low": 306.2,
      "volume": 837127
    },
    {
      "date": "2024-06-10",
      "price": 315.8,
      "high": 318.2,
      "low": 313.8,
      "volume": 400145
    },
    {
      "date": "2024-06-12",
      "price": 306.3,
      "high": 312.3,
      "low": 306.2,
      "volume": 677476
    },
    {
      "date": "2024-06-14",
      "price": 298.2,
      "high": 304.1,
      "low": 298.2,
      "volume": 793413
    },
    {
      "date": "2024-06-18",
      "price": 300.6,
      "high": 302.0,
      "low": 294.8,
      "volume": 590835
    },
    {
      "date": "2024-06-20",
      "price": 299.0,
      "high": 299.7,
      "low": 296.2,
      "volume": 575770
    },
    {
      "date": "2024-06-24",
      "price": 305.5,
      "high": 306.8,
      "low": 300.5,
      "volume": 664406
    },
    {
      "date": "2024-06-26",
      "price": 308.3,
      "high": 312.0,
      "low": 305.3,
      "volume": 856408
    },
    {
      "date": "2024-06-28",
      "price": 307.6,
      "high": 310.7,
      "low": 304.9,
      "volume": 353836
    },
    {
      "date": "2024-07-02",
      "price": 303.2,
      "high": 308.2,
      "low": 302.8,
      "volume": 524556
    },
    {
      "date": "2024-07-04",
      "price": 301.4,
      "high": 304.3,
      "low": 299.3,
      "volume": 335191
    },
    {
      "date": "2024-07-08",
      "price": 293.0,
      "high": 294.9,
      "low": 291.7,
      "volume": 451464
    },
    {
      "date": "2024-07-10",
      "price": 291.1,
      "high": 291.5,
      "low": 286.6,
      "volume": 438555
    },
    {
      "date": "2024-07-12",
      "price": 296.9,
      "high": 297.2,
      "low": 292.6,
      "volume": 537629
    },
    {
      "date": "2024-07-16",
      "price": 294.2,
      "high": 295.2,
      "low": 291.1,
      "volume": 612781
    },
    {
      "date": "2024-07-18",
      "price": 301.8,
      "high": 303.3,
      "low": 299.7,
      "volume": 653239
    },
    {
      "date": "2024-07-22",
      "price": 322.2,
      "high": 325.0,
      "low": 317.1,
      "volume": 821523
    },
    {
      "date": "2024-07-24",
      "price": 316.3,
      "high": 320.4,
      "low": 315.2,
      "volume": 467301
    },
    {
      "date": "2024-07-26",
      "price": 317.0,
      "high": 319.2,
      "low": 315.1,
      "volume": 421098
    },
    {
      "date": "2024-07-30",
      "price": 311.7,
      "high": 314.0,
      "low": 310.9,
      "volume": 497687
    },
    {
      "date": "2024-08-01",
      "price": 306.4,
      "high": 312.6,
      "low": 306.2,
      "volume": 356707
    },
    {
      "date": "2024-08-05",
      "price": 294.5,
      "high": 298.5,
      "low": 290.5,
      "volume": 889748
    },
    {
      "date": "2024-08-07",
      "price": 299.1,
      "high": 299.2,
      "low": 292.6,
      "volume": 498730
    },
    {
      "date": "2024-08-09",
      "price": 299.8,
      "high": 302.4,
      "low": 297.9,
      "volume": 336595
    },
    {
      "date": "2024-08-13",
      "price": 301.8,
      "high": 301.8,
      "low": 296.1,
      "volume": 369473
    },
    {
      "date": "2024-08-15",
      "price": 302.3,
      "high": 303.8,
      "low": 298.1,
      "volume": 376588
    },
    {
      "date": "2024-08-19",
      "price": 303.9,
      "high": 305.0,
      "low": 300.3,
      "volume": 397524
    },
    {
      "date": "2024-08-21",
      "price": 302.5,
      "high": 302.5,
      "low": 300.0,
      "volume": 310108
    },
    {
      "date": "2024-08-23",
      "price": 304.9,
      "high": 305.6,
      "low": 302.3,
      "volume": 327156
    },
    {
      "date": "2024-08-27",
      "price": 305.7,
      "high": 310.5,
      "low": 305.7,
      "volume": 470242
    },
    {
      "date": "2024-08-29",
      "price": 306.8,
      "high": 307.6,
      "low": 303.5,
      "volume": 250653
    },
    {
      "date": "2024-09-02",
      "price": 307.1,
      "high": 309.1,
      "low": 305.5,
      "volume": 243969
    },
    {
      "date": "2024-09-04",
      "price": 298.9,
      "high": 299.2,
      "low": 295.6,
      "volume": 500618
    },
    {
      "date": "2024-09-06",
      "price": 295.2,
      "high": 300.8,
      "low": 295.2,
      "volume": 348394
    },
    {
      "date": "2024-09-10",
      "price": 292.3,
      "high": 297.2,
      "low": 292.3,
      "volume": 583533
    },
    {
      "date": "2024-09-12",
      "price": 297.8,
      "high": 302.7,
      "low": 295.7,
      "volume": 640926
    },
    {
      "date": "2024-09-16",
      "price": 308.8,
      "high": 309.5,
      "low": 303.0,
      "volume": 489830
    },
    {
      "date": "2024-09-18",
      "price": 311.4,
      "high": 314.4,
      "low": 309.3,
      "volume": 435815
    },
    {
      "date": "2024-09-20",
      "price": 322.0,
      "high": 326.0,
      "low": 322.0,
      "volume": 1320685
    },
    {
      "date": "2024-09-24",
      "price": 322.0,
      "high": 326.1,
      "low": 322.0,
      "volume": 373984
    },
    {
      "date": "2024-09-26",
      "price": 327.6,
      "high": 327.6,
      "low": 322.2,
      "volume": 519084
    },
    {
      "date": "2024-09-30",
      "price": 334.1,
      "high": 336.8,
      "low": 331.0,
      "volume": 620838
    },
    {
      "date": "2024-10-02",
      "price": 343.9,
      "high": 345.5,
      "low": 338.1,
      "volume": 655509
    },
    {
      "date": "2024-10-04",
      "price": 350.1,
      "high": 350.5,
      "low": 343.7,
      "volume": 557760
    },
    {
      "date": "2024-10-08",
      "price": 341.1,
      "high": 345.0,
      "low": 340.2,
      "volume": 475653
    },
    {
      "date": "2024-10-10",
      "price": 346.2,
      "high": 347.2,
      "low": 343.6,
      "volume": 343841
    },
    {
      "date": "2024-10-14",
      "price": 350.0,
      "high": 350.8,
      "low": 348.0,
      "volume": 339154
    },
    {
      "date": "2024-10-16",
      "price": 347.1,
      "high": 349.3,
      "low": 344.0,
      "volume": 432043
    },
    {
      "date": "2024-10-18",
      "price": 341.2,
      "high": 349.6,
      "low": 340.5,
      "volume": 442552
    },
    {
      "date": "2024-10-22",
      "price": 332.0,
      "high": 337.8,
      "low": 331.5,
      "volume": 490494
    },
    {
      "date": "2024-10-24",
      "price": 328.3,
      "high": 334.4,
      "low": 328.3,
      "volume": 319640
    },
    {
      "date": "2024-10-28",
      "price": 334.2,
      "high": 342.0,
      "low": 328.7,
      "volume": 664641
    },
    {
      "date": "2024-10-30",
      "price": 334.8,
      "high": 334.8,
      "low": 330.8,
      "volume": 435883
    },
    {
      "date": "2024-11-01",
      "price": 333.5,
      "high": 333.6,
      "low": 329.1,
      "volume": 397246
    },
    {
      "date": "2024-11-05",
      "price": 334.2,
      "high": 336.0,
      "low": 332.9,
      "volume": 270595
    },
    {
      "date": "2024-11-07",
      "price": 330.3,
      "high": 337.3,
      "low": 330.3,
      "volume": 553562
    },
    {
      "date": "2024-11-11",
      "price": 320.9,
      "high": 323.2,
      "low": 318.9,
      "volume": 464000
    },
    {
      "date": "2024-11-13",
      "price": 310.7,
      "high": 318.2,
      "low": 310.7,
      "volume": 453765
    },
    {
      "date": "2024-11-15",
      "price": 319.5,
      "high": 320.6,
      "low": 312.5,
      "volume": 466390
    },
    {
      "date": "2024-11-19",
      "price": 315.9,
      "high": 318.3,
      "low": 313.5,
      "volume": 271380
    },
    {
      "date": "2024-11-21",
      "price": 313.6,
      "high": 318.5,
      "low": 312.4,
      "volume": 476874
    },
    {
      "date": "2024-11-25",
      "price": 317.2,
      "high": 317.8,
      "low": 314.3,
      "volume": 710803
    },
    {
      "date": "2024-11-27",
      "price": 313.0,
      "high": 315.0,
      "low": 310.7,
      "volume": 357345
    },
    {
      "date": "2024-11-29",
      "price": 310.6,
      "high": 312.2,
      "low": 308.9,
      "volume": 399608
    },
    {
      "date": "2024-12-03",
      "price": 318.6,
      "high": 319.9,
      "low": 312.2,
      "volume": 693948
    },
    {
      "date": "2024-12-05",
      "price": 323.6,
      "high": 324.7,
      "low": 321.4,
      "volume": 299065
    },
    {
      "date": "2024-12-09",
      "price": 328.5,
      "high": 328.5,
      "low": 321.5,
      "volume": 583178
    },
    {
      "date": "2024-12-11",
      "price": 330.2,
      "high": 331.3,
      "low": 325.0,
      "volume": 396356
    },
    {
      "date": "2024-12-13",
      "price": 323.6,
      "high": 326.1,
      "low": 323.1,
      "volume": 256367
    },
    {
      "date": "2024-12-17",
      "price": 314.9,
      "high": 317.1,
      "low": 314.0,
      "volume": 479528
    },
    {
      "date": "2024-12-19",
      "price": 301.5,
      "high": 304.6,
      "low": 299.8,
      "volume": 609948
    },
    {
      "date": "2024-12-23",
      "price": 299.0,
      "high": 300.8,
      "low": 297.6,
      "volume": 296308
    },
    {
      "date": "2024-12-30",
      "price": 300.8,
      "high": 301.7,
      "low": 298.4,
      "volume": 525295
    },
    {
      "date": "2025-01-03",
      "price": 306.5,
      "high": 307.2,
      "low": 302.2,
      "volume": 405801
    },
    {
      "date": "2025-01-07",
      "price": 309.8,
      "high": 312.4,
      "low": 307.1,
      "volume": 556614
    },
    {
      "date": "2025-01-09",
      "price": 311.1,
      "high": 313.4,
      "low": 305.3,
      "volume": 654210
    },
    {
      "date": "2025-01-13",
      "price": 317.2,
      "high": 319.5,
      "low": 312.4,
      "volume": 696680
    },
    {
      "date": "2025-01-15",
      "price": 333.8,
      "high": 336.5,
      "low": 328.2,
      "volume": 653709
    },
    {
      "date": "2025-01-17",
      "price": 332.0,
      "high": 337.1,
      "low": 331.1,
      "volume": 662226
    },
    {
      "date": "2025-01-21",
      "price": 334.3,
      "high": 335.9,
      "low": 332.0,
      "volume": 563093
    },
    {
      "date": "2025-01-23",
      "price": 332.0,
      "high": 333.7,
      "low": 329.4,
      "volume": 577416
    },
    {
      "date": "2025-01-27",
      "price": 333.3,
      "high": 333.8,
      "low": 326.4,
      "volume": 459400
    },
    {
      "date": "2025-01-29",
      "price": 338.9,
      "high": 352.7,
      "low": 338.9,
      "volume": 1426970
    },
    {
      "date": "2025-01-31",
      "price": 339.0,
      "high": 346.0,
      "low": 338.5,
      "volume": 615784
    },
    {
      "date": "2025-02-04",
      "price": 336.6,
      "high": 338.5,
      "low": 334.2,
      "volume": 499796
    },
    {
      "date": "2025-02-06",
      "price": 334.0,
      "high": 337.5,
      "low": 332.1,
      "volume": 613854
    },
    {
      "date": "2025-02-10",
      "price": 312.6,
      "high": 313.1,
      "low": 306.7,
      "volume": 1336935
    },
    {
      "date": "2025-02-12",
      "price": 316.8,
      "high": 321.2,
      "low": 314.4,
      "volume": 734727
    },
    {
      "date": "2025-02-14",
      "price": 323.1,
      "high": 325.9,
      "low": 320.7,
      "volume": 587295
    },
    {
      "date": "2025-02-18",
      "price": 329.6,
      "high": 331.8,
      "low": 327.2,
      "volume": 329272
    },
    {
      "date": "2025-02-20",
      "price": 317.8,
      "high": 321.0,
      "low": 317.3,
      "volume": 693885
    },
    {
      "date": "2025-02-24",
      "price": 324.0,
      "high": 325.5,
      "low": 320.1,
      "volume": 403067
    },
    {
      "date": "2025-02-26",
      "price": 329.7,
      "high": 332.6,
      "low": 327.6,
      "volume": 443623
    },
    {
      "date": "2025-02-28",
      "price": 319.7,
      "high": 326.7,
      "low": 318.0,
      "volume": 1217285
    },
    {
      "date": "2025-03-04",
      "price": 312.6,
      "high": 312.6,
      "low": 308.1,
      "volume": 736933
    },
    {
      "date": "2025-03-06",
      "price": 331.4,
      "high": 332.4,
      "low": 323.2,
      "volume": 979746
    },
    {
      "date": "2025-03-10",
      "price": 335.0,
      "high": 337.4,
      "low": 329.0,
      "volume": 874645
    },
    {
      "date": "2025-03-12",
      "price": 330.0,
      "high": 336.6,
      "low": 329.9,
      "volume": 447859
    },
    {
      "date": "2025-03-14",
      "price": 329.0,
      "high": 331.0,
      "low": 323.4,
      "volume": 590777
    },
    {
      "date": "2025-03-18",
      "price": 340.6,
      "high": 342.0,
      "low": 334.5,
      "volume": 707436
    },
    {
      "date": "2025-03-20",
      "price": 340.0,
      "high": 343.7,
      "low": 336.0,
      "volume": 499132
    },
    {
      "date": "2025-03-24",
      "price": 333.2,
      "high": 338.2,
      "low": 332.7,
      "volume": 405420
    },
    {
      "date": "2025-03-26",
      "price": 323.7,
      "high": 324.8,
      "low": 320.5,
      "volume": 662929
    },
    {
      "date": "2025-03-28",
      "price": 314.2,
      "high": 319.3,
      "low": 311.9,
      "volume": 497342
    },
    {
      "date": "2025-04-01",
      "price": 317.2,
      "high": 321.4,
      "low": 316.8,
      "volume": 394219
    },
    {
      "date": "2025-04-03",
      "price": 302.8,
      "high": 305.6,
      "low": 299.6,
      "volume": 787749
    },
    {
      "date": "2025-04-07",
      "price": 305.0,
      "high": 308.0,
      "low": 282.2,
      "volume": 1246984
    },
    {
      "date": "2025-04-09",
      "price": 297.6,
      "high": 297.8,
      "low": 290.2,
      "volume": 828520
    },
    {
      "date": "2025-04-11",
      "price": 308.0,
      "high": 310.8,
      "low": 303.4,
      "volume": 552345
    },
    {
      "date": "2025-04-15",
      "price": 308.8,
      "high": 315.1,
      "low": 308.8,
      "volume": 444106
    },
    {
      "date": "2025-04-22",
      "price": 314.4,
      "high": 316.0,
      "low": 308.4,
      "volume": 635917
    },
    {
      "date": "2025-04-24",
      "price": 326.3,
      "high": 327.8,
      "low": 322.7,
      "volume": 546416
    },
    {
      "date": "2025-04-28",
      "price": 347.0,
      "high": 347.7,
      "low": 337.8,
      "volume": 811224
    },
    {
      "date": "2025-04-30",
      "price": 335.2,
      "high": 352.6,
      "low": 332.7,
      "volume": 1186130
    },
    {
      "date": "2025-05-05",
      "price": 339.5,
      "high": 341.2,
      "low": 337.6,
      "volume": 596451
    },
    {
      "date": "2025-05-07",
      "price": 344.0,
      "high": 346.6,
      "low": 338.6,
      "volume": 667976
    },
    {
      "date": "2025-05-09",
      "price": 340.7,
      "high": 344.8,
      "low": 338.9,
      "volume": 713665
    },
    {
      "date": "2025-05-13",
      "price": 348.2,
      "high": 348.2,
      "low": 341.9,
      "volume": 571495
    },
    {
      "date": "2025-05-15",
      "price": 357.8,
      "high": 357.8,
      "low": 348.8,
      "volume": 733364
    },
    {
      "date": "2025-05-19",
      "price": 361.2,
      "high": 361.2,
      "low": 356.8,
      "volume": 438053
    },
    {
      "date": "2025-05-21",
      "price": 369.3,
      "high": 369.3,
      "low": 364.1,
      "volume": 552757
    },
    {
      "date": "2025-05-23",
      "price": 376.4,
      "high": 381.9,
      "low": 372.6,
      "volume": 708903
    },
    {
      "date": "2025-05-27",
      "price": 379.3,
      "high": 379.3,
      "low": 374.5,
      "volume": 455391
    },
    {
      "date": "2025-05-30",
      "price": 366.0,
      "high": 368.6,
      "low": 362.5,
      "volume": 1947908
    },
    {
      "date": "2025-06-03",
      "price": 367.8,
      "high": 374.4,
      "low": 367.1,
      "volume": 525085
    },
    {
      "date": "2025-06-05",
      "price": 372.4,
      "high": 374.7,
      "low": 370.8,
      "volume": 422527
    },
    {
      "date": "2025-06-10",
      "price": 367.7,
      "high": 373.2,
      "low": 367.6,
      "volume": 494352
    },
    {
      "date": "2025-06-12",
      "price": 375.6,
      "high": 378.5,
      "low": 372.6,
      "volume": 333994
    },
    {
      "date": "2025-06-16",
      "price": 398.5,
      "high": 403.0,
      "low": 387.7,
      "volume": 924110
    },
    {
      "date": "2025-06-18",
      "price": 396.7,
      "high": 401.7,
      "low": 394.7,
      "volume": 762328
    },
    {
      "date": "2025-06-20",
      "price": 389.8,
      "high": 396.4,
      "low": 387.2,
      "volume": 958493
    },
    {
      "date": "2025-06-24",
      "price": 378.7,
      "high": 387.9,
      "low": 373.8,
      "volume": 753645
    },
    {
      "date": "2025-06-26",
      "price": 364.6,
      "high": 378.6,
      "low": 363.2,
      "volume": 1052706
    },
    {
      "date": "2025-06-30",
      "price": 372.0,
      "high": 372.0,
      "low": 368.5,
      "volume": 766073
    },
    {
      "date": "2025-07-02",
      "price": 378.3,
      "high": 379.0,
      "low": 373.7,
      "volume": 363097
    },
    {
      "date": "2025-07-04",
      "price": 376.0,
      "high": 377.6,
      "low": 373.8,
      "volume": 247052
    },
    {
      "date": "2025-07-08",
      "price": 387.0,
      "high": 387.0,
      "low": 379.0,
      "volume": 616266
    },
    {
      "date": "2025-07-10",
      "price": 388.2,
      "high": 392.4,
      "low": 386.8,
      "volume": 386623
    },
    {
      "date": "2025-07-14",
      "price": 385.8,
      "high": 391.6,
      "low": 384.0,
      "volume": 363849
    },
    {
      "date": "2025-07-16",
      "price": 386.0,
      "high": 388.4,
      "low": 383.7,
      "volume": 594732
    },
    {
      "date": "2025-07-18",
      "price": 382.4,
      "high": 388.1,
      "low": 371.3,
      "volume": 1018432
    },
    {
      "date": "2025-07-22",
      "price": 388.1,
      "high": 388.1,
      "low": 380.3,
      "volume": 476691
    },
    {
      "date": "2025-07-24",
      "price": 390.5,
      "high": 396.6,
      "low": 390.4,
      "volume": 423598
    },
    {
      "date": "2025-07-28",
      "price": 385.4,
      "high": 391.7,
      "low": 385.4,
      "volume": 608590
    },
    {
      "date": "2025-07-30",
      "price": 383.7,
      "high": 389.8,
      "low": 383.7,
      "volume": 373591
    },
    {
      "date": "2025-08-01",
      "price": 383.4,
      "high": 387.6,
      "low": 382.4,
      "volume": 260970
    },
    {
      "date": "2025-08-05",
      "price": 387.7,
      "high": 387.7,
      "low": 383.6,
      "volume": 452994
    },
    {
      "date": "2025-08-07",
      "price": 368.8,
      "high": 374.6,
      "low": 367.7,
      "volume": 825827
    },
    {
      "date": "2025-08-11",
      "price": 372.4,
      "high": 374.3,
      "low": 370.6,
      "volume": 331392
    },
    {
      "date": "2025-08-13",
      "price": 375.3,
      "high": 377.3,
      "low": 372.0,
      "volume": 330883
    },
    {
      "date": "2025-08-15",
      "price": 380.5,
      "high": 381.1,
      "low": 377.0,
      "volume": 307459
    },
    {
      "date": "2025-08-19",
      "price": 375.6,
      "high": 378.8,
      "low": 374.5,
      "volume": 495690
    },
    {
      "date": "2025-08-21",
      "price": 372.4,
      "high": 378.8,
      "low": 369.7,
      "volume": 367552
    },
    {
      "date": "2025-08-25",
      "price": 372.2,
      "high": 374.4,
      "low": 369.4,
      "volume": 366582
    },
    {
      "date": "2025-08-27",
      "price": 368.8,
      "high": 377.5,
      "low": 368.4,
      "volume": 464827
    },
    {
      "date": "2025-08-29",
      "price": 365.7,
      "high": 368.9,
      "low": 363.4,
      "volume": 399550
    },
    {
      "date": "2025-09-02",
      "price": 364.1,
      "high": 365.6,
      "low": 360.9,
      "volume": 297711
    },
    {
      "date": "2025-09-04",
      "price": 358.3,
      "high": 359.1,
      "low": 355.0,
      "volume": 436775
    },
    {
      "date": "2025-09-08",
      "price": 361.5,
      "high": 365.9,
      "low": 359.5,
      "volume": 409392
    },
    {
      "date": "2025-09-10",
      "price": 363.7,
      "high": 368.5,
      "low": 361.2,
      "volume": 493720
    },
    {
      "date": "2025-09-12",
      "price": 370.5,
      "high": 372.5,
      "low": 368.9,
      "volume": 369843
    },
    {
      "date": "2025-09-16",
      "price": 367.0,
      "high": 371.0,
      "low": 367.0,
      "volume": 333074
    },
    {
      "date": "2025-09-18",
      "price": 359.7,
      "high": 363.0,
      "low": 359.7,
      "volume": 395313
    },
    {
      "date": "2025-09-22",
      "price": 361.3,
      "high": 362.5,
      "low": 358.4,
      "volume": 386303
    },
    {
      "date": "2025-09-24",
      "price": 374.5,
      "high": 374.8,
      "low": 364.4,
      "volume": 772666
    }
  ],
  "last_updated": "2025-09-26T04:26:59",
  "difficulty_rating": 3,
  "hint_categories": [
    "market_cap",
    "sector",
    "employees",
    "price_range",
    "location",
    "description"
  ]
}